Workbook

Sheet KPI Dashboard
A1: YoungXCode — KPI Dashboard
A2: Auto-calculated from Clients, Projects, Tasks, Invoices sheets. Update target values (yellow) as needed.
A4: KPI | B4: Formula / Calculation Method | C4: Current Value | D4: Target | E4: Status | F4: Category
A5: Monthly Recurring Revenue (MRR) | B5: Total Invoiced Amount (incl. GST) / Number of Active Months | C5: =Calc!B3/Calc!B4 -> 877578.46 | D5: 1000000 | E5: =IF(C5>=D5,"On Track","Below Target") -> Below Target | F5: Revenue
A6: Average Project Value | B6: AVERAGE(Project Budget) across all projects | C6: =AVERAGE(Projects!G2:G81) -> 1169068.9 | D6: 1200000 | E6: =IF(C6>=D6,"On Track","Below Target") -> Below Target | F6: Revenue
A7: Invoice Collection Rate | B7: SUM(Paid Invoices Total) / SUM(Total Invoiced) x 100 | C7: =Calc!B5/Calc!B3 -> 0.51696592 | D7: 0.85 | E7: =IF(C7>=D7,"On Track","Below Target") -> Below Target | F7: Revenue
A8: Overdue Amount | B8: SUM(Total Amount) where Payment Status is Overdue/Unpaid/Partially Paid AND Due Date < Today | C8: =Calc!B6 -> 14412610 | D8: 500000 | E8: =IF(C8<=D8,"On Track","Above Target") -> Above Target | F8: Revenue
A9: On-Time Delivery Rate | B9: COUNT(Completed Projects, Actual End <= Deadline) / COUNT(Completed Projects) x 100 | C9: =Calc!B8/Calc!B7 -> 0.29166667 | D9: 0.9 | E9: =IF(C9>=D9,"On Track","Below Target") -> Below Target | F9: Project
A10: Average Project Duration (days) | B10: AVERAGE(Actual End Date - Start Date) for Completed Projects | C10: =Calc!B9/Calc!B10 -> 141.48936 | D10: 120 | E10: =IF(C10<=D10,"On Track","Above Target") -> Above Target | F10: Project
A11: Budget Overrun Rate | B11: COUNT(Projects where Amount Spent > Budget) / COUNT(Total Projects) x 100 | C11: =Calc!B12/Calc!B11 -> 0.2875 | D11: 0.15 | E11: =IF(C11<=D11,"On Track","Above Target") -> Above Target | F11: Project
A12: Task Completion Rate | B12: COUNT(Tasks where Status = Completed) / COUNT(Total Tasks) x 100 | C12: =Calc!B14/Calc!B13 -> 0.78666667 | D12: 0.85 | E12: =IF(C12>=D12,"On Track","Below Target") -> Below Target | F12: Team
A13: Average Hours per Task | B13: AVERAGE(Actual Hours) across all tasks | C13: =Calc!B15/Calc!B13 -> 38.671667 | D13: 35 | E13: =IF(C13<=D13,"On Track","Above Target") -> Above Target | F13: Team
A14: Team Utilization % | B14: SUM(Actual Hours) / SUM(Estimated Hours) x 100 | C14: =Calc!B15/Calc!B16 -> 0.97959166 | D14: 0.9 | E14: =IF(C14>=D14,"On Track","Below Target") -> On Track | F14: Team
A15: Client Retention Rate | B15: COUNT(Clients with Total Projects >= 1) / COUNT(Total Clients) x 100 | C15: =Calc!B18/Calc!B17 -> 0.84 | D15: 0.8 | E15: =IF(C15>=D15,"On Track","Below Target") -> On Track | F15: Client
A16: Average Projects per Client | B16: AVERAGE(Total Projects per Client) | C16: =AVERAGE(Clients!F2:F51) -> 1.6 | D16: 2 | E16: =IF(C16>=D16,"On Track","Below Target") -> Below Target | F16: Client

Sheet Calc
A1: Helper Calculations
A2: Label | B2: Value
A3: Total Invoiced (incl GST) | B3: =SUM(Invoices!I2:I61) -> 29837668
A4: Active Months Span | B4: =DATEDIF(MIN(Invoices!C2:C61),MAX(Invoices!C2:C61),"m")+1 -> 34
A5: Total Paid Amount | B5: =SUMIF(Invoices!F2:F61,"Paid",Invoices!I2:I61) -> 15425057
A6: Total Overdue Amount | B6: =SUMIF(Invoices!J2:J61,TRUE(),Invoices!I2:I61) -> 14412610
A7: Completed Projects Count | B7: =COUNTIF(Projects!I2:I81,"Completed") -> 48
A8: On-Time Completed Count | B8: =SUMPRODUCT((Projects!I2:I81="Completed")*(Projects!F2:F81<>"")*(Projects!F2:F81<=Projects!E2:E81)) -> 14
A9: Sum Duration (Completed, days) | B9: =SUMPRODUCT((Projects!I2:I81="Completed")*(Projects!F2:F81<>"")*(Projects!F2:F81-Projects!D2:D81)) -> 6650
A10: Completed Projects with Valid End Date | B10: =SUMPRODUCT((Projects!I2:I81="Completed")*(Projects!F2:F81<>"")*1) -> 47
A11: Total Projects Count | B11: =COUNTA(Projects!A2:A81) -> 80
A12: Overrun Projects Count | B12: =SUMPRODUCT((Projects!H2:H81>Projects!G2:G81)*1) -> 23
A13: Total Tasks Count | B13: =COUNTA(Tasks!A2:A301) -> 300
A14: Completed Tasks Count | B14: =COUNTIF(Tasks!I2:I301,"Completed") -> 236
A15: Sum Actual Hours | B15: =SUM(Tasks!H2:H301) -> 11601.5
A16: Sum Estimated Hours | B16: =SUM(Tasks!G2:G301) -> 11843.2
A17: Total Clients Count | B17: =COUNTA(Clients!A2:A51) -> 50
A18: Clients with Projects >=1 | B18: =COUNTIF(Clients!F2:F51,">=1") -> 42

Sheet Clients
A1: client_id | B1: client_name | C1: city | D1: industry | E1: join_date | F1: total_projects | G1: total_revenue
A2: CL1000 | B2: Apex Systems | C2: Lucknow | D2: Logistics | E2: 44730 | F2: 1 | G2: 1150740.9
A3: CL1001 | B3: Nova Corp | C3: Bangalore | D3: E-Commerce | E3: 44060 | F3: 2 | G3: 854257.39
A4: CL1002 | B4: Pixel Works | C4: Chennai | D4: Real Estate | E4: 45123 | F4: 4 | G4: 489884.4
A5: CL1003 | B5: Quantum Labs | C5: Mumbai | D5: Media | E5: 44102 | F5: 0 | G5: 1492621.2
A6: CL1004 | B6: Grand Systems | C6: Bangalore | D6: Retail | E6: 45119 | F6: 2 | G6: 3173088.7
A7: CL1005 | B7: Apex Corp | C7: Lucknow | D7: Retail | E7: 45451 | F7: 3 | G7: 209383.83
A8: CL1006 | B8: Cloud Technologies | C8: Pune | D8: Education | E8: 44416 | F8: 1 | G8: 0
A9: CL1007 | B9: Tech Hub | C9: Indore | D9: Fintech | E9: 44841 | F9: 2 | G9: 0
A10: CL1008 | B10: Swift Solutions | C10: Indore | D10: Media | E10: 44907 | F10: 2 | G10: 80360.31
A11: CL1009 | B11: Nova Systems | C11: Surat | D11: Hospitality | E11: 45585 | F11: 2 | G11: 0
A12: CL1010 | B12: Quantum Works | C12: Bangalore | D12: Education | E12: 45313 | F12: 1 | G12: 763382.97
A13: CL1011 | B13: Crest Hub | C13: Ahmedabad | D13: Healthcare | E13: 45918 | F13: 0 | G13: 2248114.2
... A51: CL1049 | B51: Grand Technologies | C51: Jaipur | D51: Hospitality | E51: 44234 | F51: 2 | G51: 685056.77

Sheet Projects
A1: project_id | B1: project_name | C1: client_name | D1: start_date | E1: deadline | F1: actual_end_date | G1: budget | H1: amount_spent | I1: status | J1: budget_utilization_pct | K1: is_overdue
A2: PRJ2000 | B2: Analytics Dashboard - Grand | C2: Grand Works | D2: 45256 | E2: 45490 | G2: 659208.02 | H2: 37616.17 | I2: Cancelled | J2: 5.71 | K2: =FALSE() -> FALSE
A3: PRJ2001 | B3: POS System - Swift | C3: Swift Solutions | D3: 45426 | E3: 45502 | F3: 45502 | G3: 2192490.6 | H3: 1609119.7 | I3: Completed | J3: 73.39 | K3: =FALSE() -> FALSE
A4: PRJ2002 | B4: Mobile App - Tech | C4: Tech Works | D4: 44762 | E4: 44804 | G4: 1374440.4 | H4: 151642.7 | I4: In Progress | J4: 11.03 | K4: =TRUE() -> TRUE
A5: PRJ2003 | B5: Website Redesign - Cloud | C5: Cloud Net | D5: 45046 | E5: 45118 | F5: 45133 | G5: 573680.88 | H5: 505107.73 | I5: Completed | J5: 88.05 | K5: =FALSE() -> FALSE
A6: PRJ2004 | B6: E-commerce Platform - Quantum | C6: Quantum Works | D6: 45338 | E6: 45368 | F6: 45394 | G6: 2319969.3 | H6: 2443642.7 | I6: Delayed | J6: 105.33 | K6: =TRUE() -> TRUE
A7: PRJ2005 | B7: Website Redesign - Crest | C7: Crest Systems | D7: 45700 | E7: 45899 | G7: 429252.22 | H7: 132078.97 | I7: Completed | J7: 30.77 | K7: =FALSE() -> FALSE
A8: PRJ2006 | B8: Payment Gateway - Swift | C8: Swift Industries | D8: 45672 | E8: 45717 | G8: 190054.92 | H8: 96723.57 | I8: On Hold | J8: 50.89 | K8: =TRUE() -> TRUE
A9: PRJ2007 | B9: Mobile App - Nova | C9: Nova Net | D9: 44884 | E9: 44928 | F9: 44943 | G9: 2135789.2 | H9: 1560908.7 | I9: Delayed | J9: 73.08 | K9: =TRUE() -> TRUE
A10: PRJ2008 | B10: Cloud Migration - Grand | C10: Grand Net | D10: 45043 | E10: 45176 | F10: 45197 | G10: 653227.6 | H10: 632019.66 | I10: Completed | J10: 96.75 | K10: =FALSE() -> FALSE
A11: PRJ2009 | B11: CRM Integration - Apex | C11: Apex Corp | D11: 45420 | E11: 45618 | G11: 1330817.6 | H11: 1003828.3 | I11: In Progress | J11: 75.43 | K11: =TRUE() -> TRUE
A12: PRJ2010 | B12: Inventory Management - Apex | C12: Apex Industries | D12: 45205 | E12: 45296 | F12: 45289 | G12: 1118340.9 | H12: 1415858.1 | I12: Completed | J12: 126.6 | K12: =FALSE() -> FALSE
A13: PRJ2011 | B13: CRM Integration - Cloud | C13: Cloud Net | D13: 44710 | E13: 44742 | F13: 44763 | G13: 2490436.3 | H13: 1825408.4 | I13: Completed | J13: 73.3 | K13: =FALSE() -> FALSE
A14: PRJ2012 | B14: ERP System - Vivid | C14: Vivid Works | D14: 45105 | E14: 45168 | F14: 45182 | G14: 2204212.1 | H14: 1909480.7 | I14: Delayed | J14: 86.63 | K14: =TRUE() -> TRUE
A15: PRJ2013 | B15: Payment Gateway - Cloud | C15: Cloud Group | D15: 45674 | E15: 45884 | F15: 45910 | G15: 1345904.7 | H15: 1346629.4 | I15: Completed | J15: 100.05 | K15: =FALSE() -> FALSE
A16: PRJ2014 | B16: Marketing Website - Grand | C16: Grand Group | D16: 45920 | E16: 45976 | F16: 45994 | G16: 697941.51 | H16: 767994.4 | I16: Delayed | J16: 110.04 | K16: =TRUE() -> TRUE
A17: PRJ2015 | B17: API Development - Tech | C17: Tech Works | D17: 44880 | E17: 44979 | F17: 44977 | G17: 1808149.9 | H17: 0 | I17: Completed | J17: 0 | K17: =FALSE() -> FALSE
A18: PRJ2016 | B18: E-commerce Platform - Vivid | C18: Vivid Industries | D18: 45597 | E18: 45752 | F18: 45740 | G18: 276131.25 | H18: 245925 | I18: Completed | J18: 89.06 | K18: =FALSE() -> FALSE
A19: PRJ2017 | B19: Marketing Website - Pixel | C19: Pixel Works | D19: 44569 | E19: 44684 | G19: 1610927.8 | H19: 456486.48 | I19: On Hold | J19: 28.34 | K19: =TRUE() -> TRUE
A20: PRJ2018 | B20: Marketing Website - Cloud | C20: Cloud Group | D20: 45691 | E20: 45901 | F20: 45886 | G20: 324091.01 | H20: 364690.84 | I20: Completed | J20: 112.53 | K20: =FALSE() -> FALSE
A21: PRJ2019 | B21: ERP System - Nova | C21: Nova Systems | D21: 45679 | E21: 45718 | G21: 1477148.4 | H21: 65626.95 | I21: Cancelled | J21: 4.44 | K21: =FALSE() -> FALSE
A22: PRJ2020 | B22: Inventory Management - Pixel | C22: Pixel Works | D22: 45193 | E22: 45316 | F22: 45376 | G22: 2431880.9 | H22: 1745975.4 | I22: Delayed | J22: 71.8 | K22: =TRUE() -> TRUE
A23: PRJ2021 | B23: Cloud Migration - Quantum | C23: Quantum Corp | D23: 45073 | E23: 45273 | F23: 45293 | G23: 2216130 | H23: 1956554.3 | I23: Completed | J23: 88.29 | K23: =FALSE() -> FALSE
A24: PRJ2022 | B24: HRMS Portal - Bright | C24: Bright Enterprises | D24: 44941 | E24: 44968 | G24: 2441704.8 | H24: 593899.56 | I24: Cancelled | J24: 24.32 | K24: =FALSE() -> FALSE
A25: PRJ2023 | B25: POS System - Grand | C25: Grand Enterprises | D25: 44612 | E25: 44687 | G25: 863854.4 | H25: 649248.02 | I25: On Hold | J25: 75.16 | K25: =TRUE() -> TRUE
A26: PRJ2024 | B26: LMS Platform - Apex | C26: Apex Industries | D26: 45070 | E26: 45168 | F26: 45197 | G26: 314834.28 | H26: 343948.6 | I26: Completed | J26: 109.25 | K26: =FALSE() -> FALSE
A27: PRJ2025 | B27: POS System - Pixel | C27: Pixel Net | D27: 45017 | E27: 45098 | G27: 1177742.9 | H27: 107830.91 | I27: Cancelled | J27: 9.16 | K27: =FALSE() -> FALSE
A28: PRJ2026 | B28: Mobile App - Crest | C28: Crest Group | D28: 45018 | E28: 45054 | G28: 1026241.7 | H28: 302764.01 | I28: In Progress | J28: 29.5 | K28: =TRUE() -> TRUE
A29: PRJ2027 | B29: Payment Gateway - Grand | C29: Grand Technologies | D29: 45133 | E29: 45252 | G29: 1029212 | H29: 809788.95 | I29: In Progress | J29: 78.68 | K29: =TRUE() -> TRUE
A30: PRJ2028 | B30: E-commerce Platform - Bright | C30: Bright Works | D30: 44618 | E30: 44677 | G30: 689977.23 | H30: 120178.11 | I30: Cancelled | J30: 17.42 | K30: =FALSE() -> FALSE
A31: PRJ2029 | B31: Mobile App - Pixel | C31: Pixel Works | D31: 44784 | E31: 44966 | F31: 44971 | G31: 1119165 | H31: 1279100.6 | I31: Completed | J31: 114.29 | K31: =FALSE() -> FALSE
A32: PRJ2030 | B32: POS System - Swift | C32: Swift Systems | D32: 45742 | E32: 45820 | F32: 45850 | G32: 1118340.9 | H32: 1044490.3 | I32: Completed | J32: 93.4 | K32: =FALSE() -> FALSE
A33: PRJ2031 | B33: API Development - Quantum | C33: Quantum Industries | D33: 44965 | E33: 45088 | F33: 45115 | G33: 2305888.6 | H33: 2260739.1 | I33: Completed | J33: 98.04 | K33: =FALSE() -> FALSE
A34: PRJ2032 | B34: Payment Gateway - Tech | C34: Tech Hub | D34: 45177 | E34: 45336 | F34: 45347 | G34: 849148.12 | H34: 860818.63 | I34: Completed | J34: 101.37 | K34: =FALSE() -> FALSE
A35: PRJ2033 | B35: ERP System - Swift | C35: Swift Solutions | D35: 44954 | E35: 45091 | G35: 978905.93 | H35: 610537.94 | I35: In Progress | J35: 62.37 | K35: =TRUE() -> TRUE
A36: PRJ2034 | B36: POS System - Silver | C36: Silver Ventures | D36: 45727 | E36: 45834 | F36: 45819 | G36: 794493.63 | H36: 631290.5 | I36: Completed | J36: 79.46 | K36: =FALSE() -> FALSE
A37: PRJ2035 | B37: Analytics Dashboard - Swift | C37: Swift Industries | D37: 45804 | E37: 46001 | F37: 46014 | G37: 1133291.5 | H37: 902287.75 | I37: Completed | J37: 79.62 | K37: =FALSE() -> FALSE
A38: PRJ2036 | B38: Mobile App - Bright | C38: Bright Enterprises | D38: 44909 | E38: 45107 | F38: 45124 | G38: 1676441.9 | H38: 1640679 | I38: Completed | J38: 97.87 | K38: =FALSE() -> FALSE
A39: PRJ2037 | B39: Analytics Dashboard - Cloud | C39: Cloud Net | D39: 45043 | E39: 45245 | F39: 45242 | G39: 411017.21 | H39: 296259.63 | I39: Completed | J39: 72.08 | K39: =FALSE() -> FALSE
A40: PRJ2038 | B40: Booking System - Silver | C40: Silver Ventures | D40: 44711 | E40: 44857 | F40: 44882 | G40: 1460393.7 | H40: 1494356.1 | I40: Completed | J40: 102.33 | K40: =FALSE() -> FALSE
A41: PRJ2039 | B41: POS System - Vivid | C41: Vivid Ventures | D41: 45380 | E41: 45472 | F41: 45501 | G41: 63584.8 | H41: 65996.83 | I41: Completed | J41: 103.79 | K41: =FALSE() -> FALSE
A42: PRJ2040 | B42: CRM Integration - Cloud | C42: Cloud Technologies | D42: 45432 | E42: 45518 | F42: 45547 | G42: 1318996.5 | H42: 953104.59 | I42: Completed | J42: 72.26 | K42: =FALSE() -> FALSE
A43: PRJ2041 | B43: Cloud Migration - Tech | C43: Tech Hub | D43: 45496 | E43: 45560 | G43: 1685565.4 | H43: 499547.21 | I43: Cancelled | J43: 29.64 | K43: =FALSE() -> FALSE
A44: PRJ2042 | B44: HRMS Portal - Urban | C44: Urban Industries | D44: 45468 | E44: 45654 | G44: 2235449.7 | H44: 286187.25 | I44: Cancelled | J44: 12.8 | K44: =FALSE() -> FALSE
A45: PRJ2043 | B45: CRM Integration - Tech | C45: Tech Works | D45: 45475 | E45: 45545 | G45: 1212952.4 | H45: 341366.14 | I45: On Hold | J45: 28.14 | K45: =TRUE() -> TRUE
A46: PRJ2044 | B46: Analytics Dashboard - Bright | C46: Bright Ventures | D46: 45129 | E46: 45355 | G46: 1237262.7 | H46: 330933.26 | I46: On Hold | J46: 26.75 | K46: =TRUE() -> TRUE
A47: PRJ2045 | B47: ERP System - Grand | C47: Grand Systems | D47: 45147 | E47: 45237 | F47: 45242 | G47: 2237915.7 | H47: 1647687.7 | I47: Completed | J47: 73.63 | K47: =FALSE() -> FALSE
A48: PRJ2046 | B48: Payment Gateway - Crest | C48: Crest Group | D48: 45346 | E48: 45553 | F48: 45551 | G48: 207360.68 | H48: 183186.51 | I48: Completed | J48: 88.34 | K48: =FALSE() -> FALSE
A49: PRJ2047 | B49: Marketing Website - Tech | C49: Tech Technologies | D49: 45413 | E49: 45458 | F49: 45469 | G49: 1004218.2 | H49: 1050822.1 | I49: Completed | J49: 104.64 | K49: =FALSE() -> FALSE
A50: PRJ2048 | B50: HRMS Portal - Nova | C50: Nova Corp | D50: 45741 | E50: 45868 | F50: 45875 | G50: 781601 | H50: 684286.98 | I50: Completed | J50: 87.55 | K50: =FALSE() -> FALSE
A51: PRJ2049 | B51: Analytics Dashboard - Grand | C51: Grand Enterprises | D51: 45664 | E51: 45885 | G51: 2009677 | H51: 1463985.3 | I51: On Hold | J51: 72.85 | K51: =TRUE() -> TRUE
A52: PRJ2050 | B52: Booking System - Crest | C52: Crest Group | D52: 45120 | E52: 45261 | F52: 45270 | G52: 873517.38 | H52: 878421.17 | I52: Completed | J52: 100.56 | K52: =FALSE() -> FALSE
A53: PRJ2051 | B53: Cloud Migration - Grand | C53: Grand Works | D53: 44900 | E53: 45049 | F53: 45098 | G53: 1358602.9 | H53: 1505492.3 | I53: Delayed | J53: 110.81 | K53: =TRUE() -> TRUE
A54: PRJ2052 | B54: Website Redesign - Silver | C54: Silver Systems | D54: 45919 | E54: 45955 | F54: 45967 | G54: 382463.74 | H54: 347186.93 | I54: Completed | J54: 90.78 | K54: =FALSE() -> FALSE
A55: PRJ2053 | B55: E-commerce Platform - Vivid | C55: Vivid Industries | D55: 45338 | E55: 45451 | F55: 45456 | G55: 876876.34 | H55: 960914.41 | I55: Completed | J55: 109.58 | K55: =FALSE() -> FALSE
A56: PRJ2054 | B56: Website Redesign - Cloud | C56: Cloud Net | D56: 45425 | E56: 45519 | G56: 1202251.8 | H56: 270154.72 | I56: Cancelled | J56: 22.47 | K56: =FALSE() -> FALSE
A57: PRJ2055 | B57: CRM Integration - Royal | C57: Royal Ventures | D57: 45021 | E57: 45217 | F57: 45243 | G57: 148632.44 | H57: 106118.14 | I57: Completed | J57: 71.4 | K57: =FALSE() -> FALSE
A58: PRJ2056 | B58: CRM Integration - Nova | C58: Nova Technologies | D58: 44603 | E58: 44792 | F58: 44785 | G58: 1210224.6 | H58: 909453.83 | I58: Completed | J58: 75.15 | K58: =FALSE() -> FALSE
A59: PRJ2057 | B59: Mobile App - Tech | C59: Tech Technologies | D59: 45086 | E59: 45312 | F59: 45335 | G59: 1537756.4 | H59: 1593986.8 | I59: Completed | J59: 103.66 | K59: =FALSE() -> FALSE
A60: PRJ2058 | B60: HRMS Portal - Grand | C60: Grand Technologies | D60: 44897 | E60: 45006 | F60: 44992 | G60: 2325773.6 | H60: 2230669.3 | I60: Completed | J60: 95.91 | K60: =FALSE() -> FALSE
A61: PRJ2059 | B61: Mobile App - Swift | C61: Swift Systems | D61: 45374 | E61: 45587 | F61: 45609 | G61: 1742005.3 | H61: 1711100.5 | I61: Completed | J61: 98.23 | K61: =FALSE() -> FALSE
A62: PRJ2060 | B62: POS System - Vivid | C62: Vivid Net | D62: 45179 | E62: 45384 | G62: 346584.91 | H62: 273348.42 | I62: In Progress | J62: 78.87 | K62: =TRUE() -> TRUE
A63: PRJ2061 | B63: Website Redesign - Pixel | C63: Pixel Works | D63: 45273 | E63: 45439 | F63: 45447 | G63: 218944 | H63: 217059.87 | I63: Completed | J63: 99.14 | K63: =FALSE() -> FALSE
A64: PRJ2062 | B64: Marketing Website - Grand | C64: Grand Enterprises | D64: 45565 | E64: 45622 | F64: 45630 | G64: 1607183.5 | H64: 1724376.6 | I64: Completed | J64: 107.29 | K64: =FALSE() -> FALSE
A65: PRJ2063 | B65: POS System - Nova | C65: Nova Systems | D65: 45453 | E65: 45528 | G65: 2415410.6 | H65: 698192.99 | I65: On Hold | J65: 28.91 | K65: =TRUE() -> TRUE
A66: PRJ2064 | B66: LMS Platform - Quantum | C66: Quantum Industries | D66: 45552 | E66: 45701 | F66: 45723 | G66: 707569.07 | H66: 766489 | I66: Completed | J66: 108.33 | K66: =FALSE() -> FALSE
A67: PRJ2065 | B67: Inventory Management - Apex | C67: Apex Corp | D67: 45133 | E67: 45278 | F67: 45292 | G67: 1446131.6 | H67: 1447122 | I67: Completed | J67: 100.07 | K67: =FALSE() -> FALSE
A68: PRJ2066 | B68: E-commerce Platform - Nova | C68: Nova Corp | D68: 45574 | E68: 45687 | F68: 45685 | G68: 919321.17 | H68: 750403.8 | I68: Completed | J68: 81.63 | K68: =FALSE() -> FALSE
A69: PRJ2067 | B69: Analytics Dashboard - Bharat | C69: Bharat Net | D69: 45127 | E69: 45299 | F69: 45296 | G69: 259751.76 | H69: 265994.53 | I69: Completed | J69: 102.4 | K69: =FALSE() -> FALSE
A70: PRJ2068 | B70: Mobile App - Tech | C70: Tech Works | D70: 45054 | E70: 45260 | F70: 45290 | G70: 1252512.3 | H70: 1323679.8 | I70: Completed | J70: 105.68 | K70: =FALSE() -> FALSE
A71: PRJ2069 | B71: Analytics Dashboard - Royal | C71: Royal Labs | D71: 45015 | E71: 45148 | G71: 800204.77 | H71: 405774.96 | I71: In Progress | J71: 50.71 | K71: =TRUE() -> TRUE
A72: PRJ2070 | B72: E-commerce Platform - Tech | C72: Tech Works | D72: 45649 | E72: 45767 | F72: 45787 | G72: 860438.68 | H72: 874450.69 | I72: Completed | J72: 101.63 | K72: =FALSE() -> FALSE
A73: PRJ2071 | B73: POS System - Grand | C73: Grand Group | D73: 45076 | E73: 45165 | F73: 45162 | G73: 823092.46 | H73: 851321.63 | I73: Completed | J73: 103.43 | K73: =FALSE() -> FALSE
A74: PRJ2072 | B74: POS System - Vivid | C74: Vivid Net | D74: 44941 | E74: 45020 | F74: 45035 | G74: 727424.09 | H74: 702192.74 | I74: Completed | J74: 96.53 | K74: =FALSE() -> FALSE
A75: PRJ2073 | B75: E-commerce Platform - Nova | C75: Nova Net | D75: 45784 | E75: 45886 | F75: 45908 | G75: 775803.83 | H75: 669050.49 | I75: Delayed | J75: 86.24 | K75: =TRUE() -> TRUE
A76: PRJ2074 | B76: ERP System - Apex | C76: Apex Systems | D76: 45655 | E76: 45717 | F76: 45705 | G76: 1405729.5 | H76: 1425181.7 | I76: Completed | J76: 101.38 | K76: =FALSE() -> FALSE
A77: PRJ2075 | B77: Analytics Dashboard - Bright | C77: Bright Ventures | D77: 45567 | E77: 45623 | G77: 1456457.3 | H77: 205096.99 | I77: Cancelled | J77: 14.08 | K77: =FALSE() -> FALSE
A78: PRJ2076 | B78: Analytics Dashboard - Bright | C78: Bright Works | D78: 44939 | E78: 44982 | F78: 44997 | G78: 329513.49 | H78: 240348.64 | I78: Completed | J78: 72.94 | K78: =FALSE() -> FALSE
A79: PRJ2077 | B79: E-commerce Platform - Grand | C79: Grand Systems | D79: 45743 | E79: 45934 | G79: 421731.17 | H79: 281631.84 | I79: In Progress | J79: 66.78 | K79: =TRUE() -> TRUE
A80: PRJ2078 | B80: Cloud Migration - Apex | C80: Apex Corp | D80: 45070 | E80: 45130 | G80: 1069626.4 | H80: 553305.72 | I80: In Progress | J80: 51.73 | K80: =TRUE() -> TRUE
A81: PRJ2079 | B81: Booking System - Crest | C81: Crest Group | D81: 45632 | E81: 45759 | F81: 45772 | G81: 778515.17 | H81: 751139.71 | I81: Completed | J81: 96.48 | K81: =FALSE() -> FALSE

Sheet Tasks
A1: task_id | B1: project_name | C1: assignee | D1: priority | E1: created_date | F1: completed_date | G1: estimated_hours | H1: actual_hours | I1: task_status | J1: hours_variance
A2: TSK3000 | B2: POS System - Vivid | C2: Tanvi Desai | D2: Medium | E2: 45525 | F2: 45565 | G2: 76.9 | H2: 53.8 | I2: Completed | J2: -23.1
A3: TSK3001 | B3: Payment Gateway - Grand | C3: Priya Singh | D3: Low | E3: 45200 | F3: 45211 | G3: 20.7 | H3: 23.8 | I3: Completed | J3: 3.1
A4: TSK3002 | B4: Website Redesign - Silver | C4: Siddharth Iyer | D4: High | E4: 46034 | F4: 46065 | G4: 24.7 | H4: 20.5 | I4: Completed | J4: -4.2
A5: TSK3003 | B5: HRMS Portal - Grand | C5: Pooja Reddy | D5: Medium | E5: 44915 | F5: 44932 | G5: 63.5 | H5: 77.8 | I5: Completed | J5: 14.3
A6: TSK3004 | B6: Website Redesign - Cloud | C6: Priya Singh | D6: Low | E6: 45454 | F6: 45496 | G6: 13.6 | H6: 11.8 | I6: Completed | J6: -1.8
A7: TSK3005 | B7: Mobile App - Nova | C7: Isha Bansal | D7: High | E7: 44926 | G7: 48.4 | H7: 35.9 | I7: Open | J7: -12.5
A8: TSK3006 | B8: CRM Integration - Nova | C8: Neha Kapoor | D8: Critical | E8: 44634 | F8: 44654 | G8: 56.6 | H8: 87.3 | I8: Completed | J8: 30.7
A9: TSK3007 | B9: CRM Integration - Nova | C9: Riya Sharma | D9: Low | E9: 44623 | F9: 44651 | G9: 59.3 | H9: 71.4 | I9: Completed | J9: 12.1
A10: TSK3008 | B10: Mobile App - Pixel | C10: Tanvi Desai | D10: High | E10: 44956 | G10: 37.1 | H10: 40.1 | I10: Open | J10: 3
A11: TSK3009 | B11: E-commerce Platform - Nova | C11: Vikram Joshi | D11: High | E11: 45794 | G11: 15.7 | H11: 7.3 | I11: Open | J11: -8.4
A12: TSK3010 | B12: POS System - Grand | C12: Ananya Rao | D12: High | E12: 44761 | F12: 44793 | G12: 77.6 | H12: 83 | I12: Completed | J12: 5.4
A13: TSK3011 | B13: Cloud Migration - Tech | C13: Sneha Patel | D13: Critical | E13: 45667 | F13: 45678 | G13: 27.7 | H13: 35.8 | I13: Completed | J13: 8.1
A14: TSK3012 | B14: E-commerce Platform - Tech | C14: Tanvi Desai | D14: Critical | E14: 45658 | F14: 45679 | G14: 21.7 | H14: 15.5 | I14: Completed | J14: -6.2
A15: TSK3013 | B15: Inventory Management - Apex | C15: Neha Kapoor | D15: High | E15: 45133 | F15: 45168 | G15: 38 | H15: 24.9 | I15: Completed | J15: -13.1
A16: TSK3014 | B16: Booking System - Crest | C16: Neha Kapoor | D16: Medium | E16: 45825 | F16: 45854 | G16: 61.3 | H16: 0 | I16: Completed | J16: -61.3
A17: TSK3015 | B17: Mobile App - Bright | C17: Pooja Reddy | D17: Medium | E17: 45021 | G17: 39.8 | H17: 1 | I17: Open | J17: -38.8
A18: TSK3016 | B18: Inventory Management - Pixel | C18: Manish Kumar | D18: Low | E18: 45272 | F18: 45308 | G18: 33.8 | H18: 27.9 | I18: Completed | J18: -5.9
A19: TSK3017 | B19: Mobile App - Swift | C19: Neha Kapoor | D19: High | E19: 45404 | F19: 45414 | G19: 40.9 | H19: 53.8 | I19: Completed | J19: 12.9
A20: TSK3018 | B20: E-commerce Platform - Vivid | C20: Ananya Rao | D20: Medium | E20: 45461 | G20: 21 | H20: 10.4 | I20: Open | J20: -10.6
A21: TSK3019 | B21: Analytics Dashboard - Bright | C21: Tanvi Desai | D21: Critical | E21: 45069 | F21: 45078 | G21: 69.4 | H21: 60.8 | I21: Completed | J21: -8.6
A22: TSK3020 | B22: CRM Integration - Tech | C22: Arjun Nair | D22: Critical | E22: 45604 | F22: 45605 | G22: 24.1 | H22: 21.7 | I22: Completed | J22: -2.4
A23: TSK3021 | B23: ERP System - Nova | C23: Ananya Rao | D23: Critical | E23: 45793 | F23: 45816 | G23: 27.9 | H23: 38 | I23: Completed | J23: 10.1
A24: TSK3022 | B24: Cloud Migration - Tech | C24: Manish Kumar | D24: Critical | E24: 45544 | G24: 20.6 | H24: 7.1 | I24: Open | J24: -13.5
A25: TSK3023 | B25: Website Redesign - Crest | C25: Manish Kumar | D25: Medium | E25: 45781 | F25: 45806 | G25: 32.1 | H25: 40.6 | I25: Completed | J25: 8.5
A26: TSK3024 | B26: POS System - Nova | C26: Manish Kumar | D26: Critical | E26: 45462 | F26: 45500 | G26: 27.9 | H26: 19.5 | I26: Completed | J26: -8.4
A27: TSK3025 | B27: ERP System - Vivid | C27: Manish Kumar | D27: Medium | E27: 45239 | G27: 3.2 | H27: 0.4 | I27: Open | J27: -2.8
A28: TSK3026 | B28: CRM Integration - Apex | C28: Ananya Rao | D28: Low | E28: 45540 | G28: 22.7 | H28: 12.7 | I28: Open | J28: -10
A29: TSK3027 | B29: HRMS Portal - Urban | C29: Siddharth Iyer | D29: Critical | E29: 45640 | G29: 31.6 | H29: 9 | I29: Open | J29: -22.6
A30: TSK3028 | B30: Analytics Dashboard - Royal | C30: Karan Mehta | D30: Low | E30: 45024 | F30: 45040 | G30: 51.2 | H30: 77.9 | I30: Completed | J30: 26.7
A31: TSK3029 | B31: CRM Integration - Royal | C31: Priya Singh | D31: High | E31: 45046 | G31: 56.9 | H31: 5.1 | I31: Open | J31: -51.8
A32: TSK3030 | B32: Website Redesign - Cloud | C32: Priya Singh | D32: Medium | E32: 45057 | F32: 45061 | G32: 24.9 | H32: 24.3 | I32: Completed | J32: -0.6
A33: TSK3031 | B33: Analytics Dashboard - Bharat | C33: Manish Kumar | D33: Critical | E33: 45232 | F33: 45244 | G33: 15.3 | H33: 10.4 | I33: Completed | J33: -4.9
A34: TSK3032 | B34: Booking System - Crest | C34: Sneha Patel | D34: Critical | E34: 45806 | F34: 45844 | G34: 13.2 | H34: 14 | I34: Completed | J34: 0.8
A35: TSK3033 | B35: Payment Gateway - Tech | C35: Priya Singh | D35: Low | E35: 45347 | F35: 45377 | G35: 72.3 | H35: 92.4 | I35: Completed | J35: 20.1
A36: TSK3034 | B36: CRM Integration - Nova | C36: Siddharth Iyer | D36: High | E36: 44691 | G36: 25.3 | H36: 21.9 | I36: Open | J36: -3.4
A37: TSK3035 | B37: HRMS Portal - Grand | C37: Ananya Rao | D37: High | E37: 44974 | F37: 44999 | G37: 68.6 | H37: 48.5 | I37: Completed | J37: -20.1
A38: TSK3036 | B38: E-commerce Platform - Nova | C38: Pooja Reddy | D38: Critical | E38: 45859 | G38: 25 | H38: 22 | I38: Open | J38: -3
A39: TSK3037 | B39: Analytics Dashboard - Swift | C39: Isha Bansal | D39: Critical | E39: 45806 | F39: 45850 | G39: 62.7 | H39: 98.7 | I39: Completed | J39: 36
A40: TSK3038 | B40: Mobile App - Bright | C40: Pooja Reddy | D40: Medium | E40: 45107 | G40: 49.4 | H40: 15.7 | I40: Open | J40: -33.7
A41: TSK3039 | B41: Booking System - Crest | C41: Aman Verma | D41: Low | E41: 45696 | F41: 45739 | G41: 55.1 | H41: 40.6 | I41: Completed | J41: -14.5
A42: TSK3040 | B42: POS System - Vivid | C42: Sneha Patel | D42: High | E42: 45492 | F42: 45516 | G42: 59.1 | H42: 40.8 | I42: Completed | J42: -18.3
A43: TSK3041 | B43: E-commerce Platform - Vivid | C43: Neha Kapoor | D43: High | E43: 45382 | F43: 45417 | G43: 70.4 | H43: 68 | I43: Completed | J43: -2.4
A44: TSK3042 | B44: Cloud Migration - Quantum | C44: Sneha Patel | D44: High | E44: 45138 | G44: 75.6 | H44: 65.8 | I44: Open | J44: -9.8
A45: TSK3043 | B45: Marketing Website - Grand | C45: Manish Kumar | D45: Critical | E45: 46039 | G45: 13 | H45: 11.3 | I45: Open | J45: -1.7
A46: TSK3044 | B46: POS System - Grand | C46: Vikram Joshi | D46: High | E46: 45169 | F46: 45195 | G46: 3.1 | H46: 3.5 | I46: Completed | J46: 0.4
A47: TSK3045 | B47: ERP System - Swift | C47: Karan Mehta | D47: Critical | E47: 45103 | F47: 45144 | G47: 75.3 | H47: 53.3 | I47: Completed | J47: -22
A48: TSK3046 | B48: Website Redesign - Cloud | C48: Karan Mehta | D48: Low | E48: 45204 | G48: 45.8 | H48: 37.7 | I48: Open | J48: -8.1
A49: TSK3047 | B49: Mobile App - Swift | C49: Riya Sharma | D49: High | E49: 45553 | F49: 45580 | G49: 11.1 | H49: 7.2 | I49: Completed | J49: -3.9
A50: TSK3048 | B50: POS System - Nova | C50: Pooja Reddy | D50: Critical | E50: 45482 | F50: 45517 | G50: 12.6 | H50: 13.3 | I50: Completed | J50: 0.7
A51: TSK3049 | B51: Analytics Dashboard - Bright | C51: Arjun Nair | D51: Critical | E51: 45757 | F51: 45784 | G51: 53.1 | H51: 76.1 | I51: Completed | J51: 23
A52: TSK3050 | B52: Analytics Dashboard - Swift | C52: Manish Kumar | D52: High | E52: 45812 | F52: 45826 | G52: 36.6 | H52: 56.8 | I52: Completed | J52: 20.2
A53: TSK3051 | B53: ERP System - Vivid | C53: Karan Mehta | D53: Low | E53: 45280 | F53: 45322 | G53: 30 | H53: 29.9 | I53: Completed | J53: -0.1
A54: TSK3052 | B54: HRMS Portal - Grand | C54: Riya Sharma | D54: High | E54: 44920 | F54: 44962 | G54: 51.9 | H54: 81.5 | I54: Completed | J54: 29.6
A55: TSK3053 | B55: API Development - Quantum | C55: Neha Kapoor | D55: Medium | E55: 44997 | G55: 18 | H55: 13.4 | I55: Open | J55: -4.6
A56: TSK3054 | B56: Analytics Dashboard - Bright | C56: Tanvi Desai | D56: Low | E56: 45622 | G56: 20.2 | H56: 14.1 | I56: Open | J56: -6.1
A57: TSK3055 | B57: Analytics Dashboard - Swift | C57: Aman Verma | D57: Low | E57: 45056 | G57: 44.1 | H57: 31.7 | I57: Open | J57: -12.4
A58: TSK3056 | B58: E-commerce Platform - Vivid | C58: Sneha Patel | D58: Low | E58: 45600 | F58: 45616 | G58: 47.9 | H58: 29.5 | I58: Completed | J58: -18.4
A59: TSK3057 | B59: E-commerce Platform - Vivid | C59: Tanvi Desai | D59: High | E59: 45786 | F59: 45794 | G59: 60.2 | H59: 64.8 | I59: Completed | J59: 4.6
A60: TSK3058 | B60: Inventory Management - Apex | C60: Siddharth Iyer | D60: High | E60: 45284 | F60: 45317 | G60: 19.3 | H60: 23.5 | I60: Completed | J60: 4.2
A61: TSK3059 | B61: HRMS Portal - Grand | C61: Ananya Rao | D61: Critical | E61: 45061 | G61: 6.7 | H61: 2.9 | I61: Open | J61: -3.8
A62: TSK3060 | B62: Payment Gateway - Cloud | C62: Arjun Nair | D62: Medium | E62: 45799 | F62: 45828 | G62: 7.7 | H62: 5.2 | I62: Completed | J62: -2.5
A63: TSK3061 | B63: Cloud Migration - Grand | C63: Ananya Rao | D63: High | E63: 45075 | F63: 45116 | G63: 47.7 | H63: 62.6 | I63: Completed | J63: 14.9
A64: TSK3062 | B64: HRMS Portal - Grand | C64: Pooja Reddy | D64: Medium | E64: 45026 | F64: 45033 | G64: 63.9 | H64: 45.7 | I64: Completed | J64: -18.2
A65: TSK3063 | B65: CRM Integration - Royal | C65: Ananya Rao | D65: Critical | E65: 45136 | G65: 34.3 | H65: 25.5 | I65: Open | J65: -8.8
A66: TSK3064 | B66: ERP System - Vivid | C66: Pooja Reddy | D66: Critical | E66: 45185 | F66: 45228 | G66: 21.9 | H66: 34 | I66: Completed | J66: 12.1
A67: TSK3065 | B67: Cloud Migration - Grand | C67: Siddharth Iyer | D67: High | E67: 45066 | G67: 9.3 | H67: 0.8 | I67: Open | J67: -8.5
A68: TSK3066 | B68: E-commerce Platform - Vivid | C68: Ananya Rao | D68: High | E68: 45739 | F68: 45775 | G68: 45.8 | H68: 58.2 | I68: Completed | J68: 12.4
A69: TSK3067 | B69: Website Redesign - Cloud | C69: Arjun Nair | D69: Medium | E69: 45609 | F69: 45628 | G69: 48.8 | H69: 46.4 | I69: Completed | J69: -2.4
A70: TSK3068 | B70: ERP System - Nova | C70: Aman Verma | D70: High | E70: 45847 | F70: 45854 | G70: 29.3 | H70: 33.9 | I70: Completed | J70: 4.6
A71: TSK3069 | B71: E-commerce Platform - Nova | C71: Manish Kumar | D71: Low | E71: 45841 | G71: 67.9 | H71: 59.6 | I71: Open | J71: -8.3
A72: TSK3070 | B72: E-commerce Platform - Grand | C72: Siddharth Iyer | D72: High | E72: 45911 | G72: 22.9 | H72: 3.7 | I72: Open | J72: -19.2
A73: TSK3071 | B73: CRM Integration - Tech | C73: Priya Singh | D73: Low | E73: 45564 | F73: 45574 | G73: 46.2 | H73: 46.2 | I73: Completed | J73: 0
A74: TSK3072 | B74: CRM Integration - Cloud | C74: Rohan Gupta | D74: High | E74: 44901 | F74: 44926 | G74: 34.7 | H74: 32.6 | I74: Completed | J74: -2.1
A75: TSK3073 | B75: Cloud Migration - Tech | C75: Priya Singh | D75: Medium | E75: 45694 | G75: 48.5 | H75: 38.6 | I75: Open | J75: -9.9
A76: TSK3074 | B76: Booking System - Crest | C76: Arjun Nair | D76: Critical | E76: 45644 | F76: 45662 | G76: 36.6 | H76: 37.5 | I76: Completed | J76: 0.9
A77: TSK3075 | B77: E-commerce Platform - Vivid | C77: Sneha Patel | D77: Critical | E77: 45407 | F77: 45440 | G77: 10.9 | H77: 11.2 | I77: Completed | J77: 0.3
A78: TSK3076 | B78: Analytics Dashboard - Bharat | C78: Riya Sharma | D78: Medium | E78: 45297 | F78: 45312 | G78: 32.8 | H78: 39.3 | I78: Completed | J78: 6.5
A79: TSK3077 | B79: Booking System - Silver | C79: Aman Verma | D79: Low | E79: 44765 | G79: 61.6 | H79: 16 | I79: Open | J79: -45.6
A80: TSK3078 | B80: POS System - Nova | C80: Neha Kapoor | D80: High | E80: 45644 | F80: 45653 | G80: 31.7 | H80: 41.3 | I80: Completed | J80: 9.6
A81: TSK3079 | B81: CRM Integration - Apex | C81: Isha Bansal | D81: Low | E81: 45521 | G81: 5.3 | H81: 0.1 | I81: Open | J81: -5.2
A82: TSK3080 | B82: CRM Integration - Cloud | C82: Aman Verma | D82: Critical | E82: 45579 | F82: 45605 | G82: 57.3 | H82: 58.3 | I82: Completed | J82: 1
A83: TSK3081 | B83: Mobile App - Tech | C83: Rohan Gupta | D83: Low | E83: 44845 | F83: 44885 | G83: 37.9 | H83: 48.9 | I83: Completed | J83: 11
A84: TSK3082 | B84: CRM Integration - Royal | C84: Manish Kumar | D84: High | E84: 45048 | F84: 45086 | G84: 33.2 | H84: 22.5 | I84: Completed | J84: -10.7
A85: TSK3083 | B85: CRM Integration - Tech | C85: Neha Kapoor | D85: Medium | E85: 45531 | F85: 45542 | G85: 8 | H85: 9.9 | I85: Completed | J85: 1.9
A86: TSK3084 | B86: Analytics Dashboard - Bright | C86: Priya Singh | D86: High | E86: 45218 | F86: 45260 | G86: 65.6 | H86: 54.9 | I86: Completed | J86: -10.7
A87: TSK3085 | B87: POS System - Pixel | C87: Pooja Reddy | D87: Critical | E87: 45061 | F87: 45103 | G87: 7.9 | H87: 12.3 | I87: Completed | J87: 4.4
A88: TSK3086 | B88: Mobile App - Swift | C88: Arjun Nair | D88: High | E88: 45567 | F88: 45605 | G88: 37 | H88: 56.4 | I88: Completed | J88: 19.4
A89: TSK3087 | B89: CRM Integration - Cloud | C89: Sneha Patel | D89: Low | E89: 45470 | F89: 45501 | G89: 36.5 | H89: 33 | I89: Completed | J89: -3.5
A90: TSK3088 | B90: ERP System - Grand | C90: Manish Kumar | D90: High | E90: 45276 | F90: 45306 | G90: 37.2 | H90: 24.4 | I90: Completed | J90: -12.8
A91: TSK3089 | B91: CRM Integration - Apex | C91: Neha Kapoor | D91: Critical | E91: 45585 | G91: 68.7 | H91: 38 | I91: Open | J91: -30.7
A92: TSK3090 | B92: Mobile App - Swift | C92: Pooja Reddy | D92: Medium | E92: 45522 | F92: 45525 | G92: 37.1 | H92: 52.3 | I92: Completed | J92: 15.2
A93: TSK3091 | B93: Cloud Migration - Tech | C93: Tanvi Desai | D93: High | E93: 45650 | F93: 45660 | G93: 76.7 | H93: 80.6 | I93: Completed | J93: 3.9
A94: TSK3092 | B94: Inventory Management - Apex | C94: Vikram Joshi | D94: Medium | E94: 45334 | F94: 45337 | G94: 21.3 | H94: 22.1 | I94: Completed | J94: 0.8
A95: TSK3093 | B95: Payment Gateway - Crest | C95: Pooja Reddy | D95: Low | E95: 45441 | G95: 32.2 | H95: 22.4 | I95: Open | J95: -9.8
A96: TSK3094 | B96: HRMS Portal - Urban | C96: Siddharth Iyer | D96: Medium | E96: 45484 | F96: 45520 | G96: 54.9 | H96: 48.5 | I96: Completed | J96: -6.4
A97: TSK3095 | B97: HRMS Portal - Urban | C97: Pooja Reddy | D97: Critical | E97: 45488 | F97: 45498 | G97: 73.5 | H97: 66.9 | I97: Completed | J97: -6.6
A98: TSK3096 | B98: E-commerce Platform - Vivid | C98: Tanvi Desai | D98: High | E98: 45749 | F98: 45755 | G98: 26.1 | H98: 25.5 | I98: Completed | J98: -0.6
A99: TSK3097 | B99: E-commerce Platform - Vivid | C99: Pooja Reddy | D99: Critical | E99: 45768 | F99: 45812 | G99: 73.2 | H99: 50.8 | I99: Completed | J99: -22.4
A100: TSK3098 | B100: Inventory Management - Apex | C100: Tanvi Desai | D100: Critical | E100: 45225 | F100: 45245 | G100: 16.1 | H100: 13.1 | I100: Completed | J100: -3
...

Sheet Invoices
A1: invoice_id | B1: client_name | C1: invoice_date | D1: invoice_amount | E1: gst | F1: payment_status | G1: due_date | H1: paid_date | I1: total_amount | J1: is_overdue
A2: INV4000 | B2: Vivid Ventures | C2: 45717 | D2: 208043.77 | E2: 37447.88 | F2: Unpaid | G2: 45732 | I2: 245491.65 | J2: =TRUE() -> TRUE
A3: INV4001 | B3: Grand Systems | C3: 44951 | D3: 748461.03 | E3: 134722.99 | F3: Paid | G3: 44981 | H3: 44964 | I3: 883184.02 | J3: =FALSE() -> FALSE
A4: INV4002 | B4: Silver Systems | C4: 45788 | D4: 446157.85 | E4: 80308.41 | F4: Paid | G4: 45818 | H4: 45813 | I4: 526466.26 | J4: =FALSE() -> FALSE
A5: INV4003 | B5: Grand Technologies | C5: 45076 | D5: 478143.53 | E5: 86065.84 | F5: Paid | G5: 45091 | H5: 45095 | I5: 564209.37 | J5: =FALSE() -> FALSE
A6: INV4004 | B6: Pixel Works | C6: 45050 | D6: 415156.27 | E6: 74728.13 | F6: Paid | G6: 45080 | I6: 489884.4 | J6: =FALSE() -> FALSE
A7: INV4005 | B7: Vivid Works | C7: 45777 | D7: 567412.3 | E7: 102134.21 | F7: Paid | G7: 45807 | H7: 45800 | I7: 669546.51 | J7: =FALSE() -> FALSE
A8: INV4006 | B8: Quantum Industries | C8: 45239 | D8: 85205.72 | E8: 15337.03 | F8: Paid | G8: 45269 | H8: 45250 | I8: 100542.75 | J8: =FALSE() -> FALSE
A9: INV4007 | B9: Quantum Corp | C9: 45245 | D9: 274865.23 | E9: 49475.74 | F9: Unpaid | G9: 45290 | I9: 324340.97 | J9: =TRUE() -> TRUE
A10: INV4008 | B10: Cloud Net | C10: 45062 | D10: 564967.19 | E10: 101694.09 | F10: Overdue | G10: 45092 | I10: 666661.28 | J10: =TRUE() -> TRUE
A11: INV4009 | B11: Quantum Enterprises | C11: 45045 | D11: 250000 | E11: 15704.28 | F11: Paid | G11: 45060 | H11: 45056 | I11: 265704.28 | J11: =FALSE() -> FALSE
A12: INV4010 | B12: Silver Ventures | C12: 45039 | D12: 539542.07 | E12: 97117.57 | F12: Unpaid | G12: 45069 | I12: 636659.64 | J12: =TRUE() -> TRUE
A13: INV4011 | B13: Crest Hub | C13: 45171 | D13: 572162.47 | E13: 102989.24 | F13: Overdue | G13: 45186 | I13: 675151.71 | J13: =TRUE() -> TRUE
A14: INV4012 | B14: Quantum Works | C14: 45943 | D14: 427944.18 | E14: 77029.95 | F14: Overdue | G14: 45973 | I14: 504974.13 | J14: =TRUE() -> TRUE
A15: INV4013 | B15: Grand Works | C15: 45457 | D15: 310058.16 | E15: 55810.47 | F15: Overdue | G15: 45472 | I15: 365868.63 | J15: =TRUE() -> TRUE
A16: INV4014 | B16: Royal Solutions | C16: 45168 | D16: 281308.6 | E16: 50635.55 | F16: Paid | G16: 45183 | H16: 45177 | I16: 331944.15 | J16: =FALSE() -> FALSE
A17: INV4015 | B17: Grand Systems | C17: 45465 | D17: 780539.46 | E17: 140497.1 | F17: Unpaid | G17: 45510 | I17: 921036.56 | J17: =TRUE() -> TRUE
A18: INV4016 | B18: Vivid Ventures | C18: 45859 | D18: 300896.64 | E18: 54161.4 | F18: Paid | G18: 45904 | H18: 45896 | I18: 355058.04 | J18: =FALSE() -> FALSE
A19: INV4017 | B19: Quantum Works | C19: 45680 | D19: 218990.54 | E19: 39418.3 | F19: Paid | G19: 45695 | H19: 45687 | I19: 258408.84 | J19: =FALSE() -> FALSE
A20: INV4018 | B20: Grand Net | C20: 45163 | D20: 597808.37 | E20: 107605.51 | F20: Paid | G20: 45178 | H20: 45161 | I20: 705413.88 | J20: =FALSE() -> FALSE
A21: INV4019 | B21: Apex Systems | C21: 45427 | D21: 387976.38 | E21: 69835.75 | F21: Paid | G21: 45442 | H21: 45448 | I21: 457812.13 | J21: =FALSE() -> FALSE
A22: INV4020 | B22: Crest Hub | C22: 44999 | D22: 646430.08 | E22: 116357.41 | F22: Overdue | G22: 45044 | I22: 762787.49 | J22: =TRUE() -> TRUE
A23: INV4021 | B23: Urban Works | C23: 45785 | D23: 271005.57 | E23: 48781 | F23: Paid | G23: 45800 | H23: 45787 | I23: 319786.57 | J23: =FALSE() -> FALSE
A24: INV4022 | B24: Urban Industries | C24: 45482 | D24: 465798.05 | E24: 83843.65 | F24: Paid | G24: 45497 | H24: 45486 | I24: 549641.7 | J24: =FALSE() -> FALSE
A25: INV4023 | B25: Quantum Labs | C25: 45294 | D25: 647383.66 | E25: 116529.06 | F25: Partially Paid | G25: 45309 | H25: 45302 | I25: 763912.72 | J25: =TRUE() -> TRUE
A26: INV4024 | B26: Grand Systems | C26: 45879 | D26: 623351.43 | E26: 112203.26 | F26: Paid | G26: 45909 | H26: 45917 | I26: 735554.69 | J26: =FALSE() -> FALSE
A27: INV4025 | B27: Tech Works | C27: 45862 | D27: 307757.1 | E27: 55396.28 | F27: Paid | G27: 45473 | H27: 45862 | I27: 363153.38 | J27: =FALSE() -> FALSE
A28: INV4026 | B28: Grand Group | C28: 45423 | D28: 307253.43 | E28: 55305.62 | F28: Partially Paid | G28: 45453 | H28: 45452 | I28: 362559.05 | J28: =TRUE() -> TRUE
A29: INV4027 | B29: Grand Works | C29: 45429 | D29: 24974.75 | E29: 4495.45 | F29: Paid | G29: 45444 | H29: 45447 | I29: 29470.2 | J29: =FALSE() -> FALSE
A30: INV4028 | B30: Quantum Industries | C30: 45636 | D30: 674867.73 | E30: 121476.19 | F30: Partially Paid | G30: 45681 | H30: 45676 | I30: 796343.92 | J30: =TRUE() -> TRUE
A31: INV4029 | B31: Apex Systems | C31: 45697 | D31: 587227.73 | E31: 105700.99 | F31: Paid | G31: 45742 | H31: 45736 | I31: 692928.72 | J31: =FALSE() -> FALSE
A32: INV4030 | B32: Quantum Enterprises | C32: 45786 | D32: 769724.35 | E32: 138550.38 | F32: Partially Paid | G32: 45816 | H32: 45817 | I32: 908274.73 | J32: =TRUE() -> TRUE
A33: INV4031 | B33: Bright Technologies | C33: 45500 | D33: 54242.21 | E33: 9763.6 | F33: Paid | G33: 45515 | H33: 45498 | I33: 64005.81 | J33: =FALSE() -> FALSE
A34: INV4032 | B34: Nova Net | C34: 45772 | D34: 718550.79 | E34: 129339.14 | F34: Paid | G34: 45817 | H34: 45804 | I34: 847889.93 | J34: =FALSE() -> FALSE
A35: INV4033 | B35: Apex Corp | C35: 45122 | D35: 124140.8 | E35: 22345.34 | F35: Overdue | G35: 45167 | I35: 146486.14 | J35: =TRUE() -> TRUE
A36: INV4034 | B36: Grand Systems | C36: 45054 | D36: 536706.26 | E36: 96607.13 | F36: Paid | G36: 45084 | H36: 45085 | I36: 633313.39 | J36: =FALSE() -> FALSE
A37: INV4035 | B37: Vivid Industries | C37: 45572 | D37: 566565.97 | E37: 101981.87 | F37: Overdue | G37: 45602 | I37: 668547.84 | J37: =TRUE() -> TRUE
A38: INV4036 | B38: Urban Industries | C38: 45854 | D38: 202216.76 | E38: 36399.02 | F38: Partially Paid | G38: 45884 | H38: 45885 | I38: 238615.78 | J38: =TRUE() -> TRUE
A39: INV4037 | B39: Grand Technologies | C39: 45150 | D39: 102413.05 | E39: 18434.35 | F39: Paid | G39: 45165 | H39: 45165 | I39: 120847.4 | J39: =FALSE() -> FALSE
A40: INV4038 | B40: Grand Enterprises | C40: 45174 | D40: 299464.21 | E40: 53903.56 | F40: Overdue | G40: 45219 | I40: 353367.77 | J40: =TRUE() -> TRUE
A41: INV4039 | B41: Cloud Group | C41: 45558 | D41: 226706.18 | E41: 40807.11 | F41: Paid | G41: 45588 | H41: 45593 | I41: 267513.29 | J41: =FALSE() -> FALSE
A42: INV4040 | B42: Grand Net | C42: 45550 | D42: 563564.83 | E42: 101441.67 | F42: Paid | G42: 45595 | H42: 45579 | I42: 665006.5 | J42: =FALSE() -> FALSE
A43: INV4041 | B43: Urban Industries | C43: 45230 | D43: 574702.77 | E43: 103446.5 | F43: Partially Paid | G43: 45245 | H43: 45238 | I43: 678149.27 | J43: =TRUE() -> TRUE
A44: INV4042 | B44: Vivid Works | C44: 45027 | D44: 253095.75 | E44: 45557.24 | F44: Overdue | G44: 45072 | I44: 298652.99 | J44: =TRUE() -> TRUE
A45: INV4043 | B45: Crest Hub | C45: 44990 | D45: 686589.02 | E45: 123586.02 | F45: Unpaid | G45: 45020 | I45: 810175.04 | J45: =TRUE() -> TRUE
A46: INV4044 | B46: Tech Works | C46: 45438 | D46: 380393.73 | E46: 68470.87 | F46: Overdue | G46: 45453 | I46: 448864.6 | J46: =TRUE() -> TRUE
A47: INV4045 | B47: Swift Solutions | C47: 45175 | D47: 68101.96 | E47: 12258.35 | F47: Overdue | G47: 45190 | I47: 80360.31 | J47: =TRUE() -> TRUE
A48: INV4046 | B48: Crest Group | C48: 45194 | D48: 662465.26 | E48: 119243.75 | F48: Paid | G48: 45209 | H48: 45199 | I48: 781709.01 | J48: =FALSE() -> FALSE
A49: INV4047 | B49: Urban Works | C49: 45099 | D49: 477172.63 | E49: 85891.07 | F49: Partially Paid | G49: 45144 | H49: 45147 | I49: 563063.7 | J49: =TRUE() -> TRUE
A50: INV4048 | B50: Nova Corp | C50: 45059 | D50: 723946.94 | E50: 130310.45 | F50: Paid | G50: 45074 | H50: 45080 | I50: 854257.39 | J50: =FALSE() -> FALSE
A51: INV4049 | B51: Apex Corp | C51: 45606 | D51: 53303.13 | E51: 9594.56 | F51: Paid | G51: 45621 | H51: 45626 | I51: 62897.69 | J51: =FALSE() -> FALSE
A52: INV4050 | B52: Silver Systems | C52: 45814 | D52: 328098.98 | E52: 59057.82 | F52: Paid | G52: 45859 | H52: 45848 | I52: 387156.8 | J52: =FALSE() -> FALSE
A53: INV4051 | B53: Crest Systems | C53: 45280 | D53: 187478.56 | E53: 33746.14 | F53: Paid | G53: 45310 | H53: 45312 | I53: 221224.7 | J53: =FALSE() -> FALSE
A54: INV4052 | B54: Cloud Group | C54: 45231 | D54: 499003.13 | E54: 89820.56 | F54: Unpaid | G54: 45246 | I54: 588823.69 | J54: =TRUE() -> TRUE
A55: INV4053 | B55: Urban Works | C55: 45531 | D55: 341353.92 | E55: 61443.71 | F55: Unpaid | G55: 45561 | I55: 402797.63 | J55: =TRUE() -> TRUE
A56: INV4054 | B56: Quantum Labs | C56: 45106 | D56: 318751.92 | E56: 57375.35 | F56: Paid | G56: 45136 | H56: 45126 | I56: 376127.27 | J56: =FALSE() -> FALSE
A57: INV4055 | B57: Nova Net | C57: 45437 | D57: 795388.08 | E57: 143169.85 | F57: Paid | G57: 45482 | H57: 45492 | I57: 938557.93 | J57: =FALSE() -> FALSE
A58: INV4056 | B58: Swift Systems | C58: 45662 | D58: 444723.89 | E58: 80050.3 | F58: Paid | G58: 45692 | H58: 45673 | I58: 524774.19 | J58: =FALSE() -> FALSE
A59: INV4057 | B59: Silver Systems | C59: 45955 | D59: 322937.39 | E59: 58128.73 | F59: Paid | G59: 45985 | H59: 45985 | I59: 381066.12 | J59: =FALSE() -> FALSE
A60: INV4058 | B60: Bharat Net | C60: 45375 | D60: 718696.53 | E60: 129365.38 | F60: Overdue | G60: 45390 | I60: 848061.91 | J60: =TRUE() -> TRUE
A61: INV4059 | B61: Quantum Labs | C61: 45893 | D61: 298797.66 | E61: 53783.58 | F61: Unpaid | G61: 45938 | I61: 352581.24 | J61: =TRUE() -> TRUE
